forecasters/__init__.py
forecasters/py.typed
forecasters-0.0.1.dist-info/METADATA
forecasters-0.0.1.dist-info/WHEEL
forecasters-0.0.1.dist-info/RECORD
