Metadata-Version: 2.3
Name: forecasters
Version: 0.0.1
Summary: Unified toolbox for pretrained time-series models to perform forecasting tasks
Requires-Python: >=3.9
